Metadata-Version: 1.0
Name: ghidra-jython-kernel
Version: 0.0.4
Summary: Jupyter kernel for Ghidra's Jython Interpreter
Home-page: UNKNOWN
Author: er28-0652
Author-email: 33626923+er28-0652@users.noreply.github.com
License: MIT
Platform: UNKNOWN
